LICENSE.txt
MANIFEST.in
README.rst
setup.py
pysamlsp/__init__.py
pysamlsp/pysamlsp.py
pysamlsp/test_pysamlsp.py
pysamlsp.egg-info/PKG-INFO
pysamlsp.egg-info/SOURCES.txt
pysamlsp.egg-info/dependency_links.txt
pysamlsp.egg-info/requires.txt
pysamlsp.egg-info/top_level.txt