Metadata-Version: 1.0
Name: pysamlsp
Version: 0.1.1
Summary: A service provider implementation for SAML2.0.
Home-page: http://pypi.python.org/pypi/pysamlsp
Author: Rob Martin @version2beta
Author-email: rob@version2beta.com
License: LICENSE.txt
Keywords: SAML2 SSO single sign on service provider only,for use with a remote IdP.
Platform: UNKNOWN
